balanced_group_system/__init__.py
balanced_group_system/available_group_scheduler.py
balanced_group_system/balanced_group_system.py
balanced_group_system/group_system.py
balanced_group_system-0.1.0.dist-info/LICENSE
balanced_group_system-0.1.0.dist-info/METADATA
balanced_group_system-0.1.0.dist-info/WHEEL
balanced_group_system-0.1.0.dist-info/RECORD
