Metadata-Version: 2.3
Name: balanced-group-system
Version: 0.1.0
Summary: A management system to create balanced groups of participants
Author: Joshua Si
Author-email: josh.j.si@proton.me
Requires-Python: >=3.9.0,<4.0.0
Classifier: Programming Language :: Python :: 3
Classifier: Programming Language :: Python :: 3.9
Classifier: Programming Language :: Python :: 3.10
Classifier: Programming Language :: Python :: 3.11
Classifier: Programming Language :: Python :: 3.12
Classifier: Programming Language :: Python :: 3.13
